README.md
setup.py
binarycookie/__init__.py
binarycookie/classes.py
binarycookie/parse.py
binarycookie/utils.py
binarycookie/version.py
binarycookie.egg-info/PKG-INFO
binarycookie.egg-info/SOURCES.txt
binarycookie.egg-info/dependency_links.txt
binarycookie.egg-info/top_level.txt